camalis/__init__.py
camalis/core.py
camalis/dataset.py
camalis/element.py
camalis/event.py
camalis/exceptions.py
camalis/main.py
camalis/model.py
camalis/utils.py
camalis/variable.py
camalis-2025.1.16.dist-info/METADATA
camalis-2025.1.16.dist-info/WHEEL
camalis-2025.1.16.dist-info/RECORD
